Metadata-Version: 1.0
Name: gaussian-and-binomial-pdfs
Version: 0.9
Summary: Gaussian and Binomial distributions
Home-page: UNKNOWN
Author: Daniel Zito
Author-email: iphonebean@icloud.com
License: UNKNOWN
Platform: UNKNOWN
